cpgzh/__init__.py
cpgzh/actor.py
cpgzh/animation.py
cpgzh/data.py
cpgzh/example.py
cpgzh/get_keys.py
cpgzh/getimg.py
cpgzh/keys.py
cpgzh/master.py
cpgzh/mouse.py
cpgzh/msyh.ttf
cpgzh/pen.py
cpgzh/runner.py
cpgzh-0.1.50.dist-info/LICENSE
cpgzh-0.1.50.dist-info/METADATA
cpgzh-0.1.50.dist-info/WHEEL
cpgzh-0.1.50.dist-info/top_level.txt
cpgzh-0.1.50.dist-info/RECORD
