Metadata-Version: 2.1
Name: cpgzh
Version: 0.1.50
Summary: pgzero的一个助手工具
Home-page: https://gitee.com/deepin-opensource/cpgzh
Author: fslong
Author-email: fsl470657570@outlook.com
License: MIT
Platform: all
Classifier: License :: OSI Approved :: MIT License
Classifier: Programming Language :: Python :: 3
Classifier: Programming Language :: Python :: 3.6
Classifier: Programming Language :: Python :: 3.7
Classifier: Programming Language :: Python :: 3.8
Classifier: Programming Language :: Python :: 3.9
Classifier: Programming Language :: Python :: 3.10
Requires-Python: >=3.6.0
Requires-Dist: guizero
Requires-Dist: pgzero
Requires-Dist: pillow
Requires-Dist: pygame
